pymdt/__init__.py
pymdt/py.typed
pymdt/wd.py
pymdt-0.0.1.dist-info/LICENSE
pymdt-0.0.1.dist-info/METADATA
pymdt-0.0.1.dist-info/WHEEL
pymdt-0.0.1.dist-info/top_level.txt
pymdt-0.0.1.dist-info/RECORD
